komminarlabs_influxdb/__init__.py
komminarlabs_influxdb/_inputs.py
komminarlabs_influxdb/_utilities.py
komminarlabs_influxdb/authorization.py
komminarlabs_influxdb/bucket.py
komminarlabs_influxdb/get_authorization.py
komminarlabs_influxdb/get_authorizations.py
komminarlabs_influxdb/get_bucket.py
komminarlabs_influxdb/get_buckets.py
komminarlabs_influxdb/get_label.py
komminarlabs_influxdb/get_labels.py
komminarlabs_influxdb/get_organization.py
komminarlabs_influxdb/get_organizations.py
komminarlabs_influxdb/get_task.py
komminarlabs_influxdb/get_tasks.py
komminarlabs_influxdb/get_user.py
komminarlabs_influxdb/get_users.py
komminarlabs_influxdb/label.py
komminarlabs_influxdb/organization.py
komminarlabs_influxdb/outputs.py
komminarlabs_influxdb/provider.py
komminarlabs_influxdb/pulumi-plugin.json
komminarlabs_influxdb/py.typed
komminarlabs_influxdb/task.py
komminarlabs_influxdb/user.py
komminarlabs_influxdb/config/__init__.py
komminarlabs_influxdb/config/__init__.pyi
komminarlabs_influxdb/config/vars.py
komminarlabs_influxdb-1.5.0.dist-info/METADATA
komminarlabs_influxdb-1.5.0.dist-info/WHEEL
komminarlabs_influxdb-1.5.0.dist-info/top_level.txt
komminarlabs_influxdb-1.5.0.dist-info/RECORD
